{
  "name": "resolver-engine-dev",
  "build": {
    "dockerfile": "Dockerfile"
  },
  "postCreateCommand": "dotnet restore",
  "customizations": {
    "vscode": {
      "extensions": [
        "ms-dotnettools.csharp",
        "ms-dotnettools.vscode-dotnet-runtime",
        "github.copilot-chat",
        "csharpier.csharpier-vscode",
        "jakubkozera.csharp-dev-tools"
      ],
      "settings": {
        "dotnet.defaultSolution": "Engine.sln",
        "editor.formatOnSave": true,
        "[csharp]": {
          "editor.defaultFormatter": "csharpier.csharpier-vscode"
        }
      }
    }
  }
}
